lsyflaskmicroapp_ys7/__init__.py
lsyflaskmicroapp_ys7/apis.py
lsyflaskmicroapp_ys7/entitys.py
lsyflaskmicroapp_ys7/error.py
lsyflaskmicroapp_ys7/schemas.py
lsyflaskmicroapp_ys7/setup.py
lsyflaskmicroapp_ys7-1.0.2.dist-info/METADATA
lsyflaskmicroapp_ys7-1.0.2.dist-info/WHEEL
lsyflaskmicroapp_ys7-1.0.2.dist-info/top_level.txt
lsyflaskmicroapp_ys7-1.0.2.dist-info/RECORD
