Metadata-Version: 2.1
Name: lsyflaskmicroapp-ys7
Version: 1.0.2
Summary: lsyflaskmicroapp_ys7
Home-page: https://gitee.com/linkeddt/lsyflaskmicroapp_ys7.git
Author: fhp
Author-email: chinafengheping@outlook.com
License: UNKNOWN
Platform: UNKNOWN
Requires-Dist: requests (==2.24.0)
Requires-Dist: cacheout (==0.11.1)
Requires-Dist: lsyflasksdkcore (==1.0.2)
Requires-Dist: lsyflaskplugin-minio (==1.0.0)
Requires-Dist: SQLAlchemy (==1.3.15)
Requires-Dist: Flask-SQLAlchemy (==2.5.1)
